evoleap_licensing/ComponentCheckoutResult.py
evoleap_licensing/ComponentEntitlementInfo.py
evoleap_licensing/ComponentInfo.py
evoleap_licensing/ComponentsStatus.py
evoleap_licensing/ControlManagerHelper.py
evoleap_licensing/ControlStrategy.py
evoleap_licensing/InstanceIdentity.py
evoleap_licensing/RegistrationResult.py
evoleap_licensing/SessionValidity.py
evoleap_licensing/UserIdentity.py
evoleap_licensing/UserInfo.py
evoleap_licensing/UserLicenseResult.py
evoleap_licensing/__init__.py
evoleap_licensing/control_logic.py
evoleap_licensing/desktop/AppSessionManager.py
evoleap_licensing/desktop/ControlManager.py
evoleap_licensing/desktop/OfflineSessionInfo.py
evoleap_licensing/desktop/__init__.py
evoleap_licensing/desktop/enumerations.py
evoleap_licensing/desktop/offline_session_info_helper.py
evoleap_licensing/enumerations/__init__.py
evoleap_licensing/enumerations/licensing_enumerations.py
evoleap_licensing/states/ControlState.py
evoleap_licensing/states/SessionControlState.py
evoleap_licensing/states/ValidatedSessionState.py
evoleap_licensing/states/ValidationState.py
evoleap_licensing/states/__init__.py
evoleap_licensing/timehandling/TimeProvider.py
evoleap_licensing/timehandling/UtcDateTime.py
evoleap_licensing/timehandling/__init__.py
evoleap_licensing/webservice/ConnectionSettings.py
evoleap_licensing/webservice/LicensingWebService.py
evoleap_licensing/webservice/WebHelper.py
evoleap_licensing/webservice/__init__.py
evoleap_licensing/webservice/jsoncomponent.py
evoleap_licensing/webservice/jsoncomponententitlement.py
evoleap_licensing/webservice/server_results.py
evoleap_licensing-1.1.3.dist-info/licenses/LICENSE
evoleap_licensing-1.1.3.dist-info/METADATA
evoleap_licensing-1.1.3.dist-info/WHEEL
evoleap_licensing-1.1.3.dist-info/top_level.txt
evoleap_licensing-1.1.3.dist-info/zip-safe
evoleap_licensing-1.1.3.dist-info/RECORD
