Metadata-Version: 2.4
Name: evoleap_licensing
Version: 1.1.3
Summary: Software licensing client API for elm, a cloud-based, enterprise grade software licensing platform.
Home-page: https://github.com/evoleap/evoleap.licensing-python
Author: evoleap
Author-email: info@evoleap.com
License: https://evoleap.com/elm_client_api_net_eula.html
Classifier: Programming Language :: Python :: 3
Classifier: Operating System :: OS Independent
License-File: LICENSE
Requires-Dist: pycryptodome
Requires-Dist: pytz
Dynamic: author
Dynamic: author-email
Dynamic: classifier
Dynamic: description
Dynamic: description-content-type
Dynamic: home-page
Dynamic: license
Dynamic: license-file
Dynamic: requires-dist
Dynamic: summary
